archicore/__init__.py
archicore/client.py
archicore/exceptions.py
archicore/py.typed
archicore-0.1.1.dist-info/licenses/LICENSE
tests/__init__.py
tests/test_client.py
archicore-0.1.1.dist-info/METADATA
archicore-0.1.1.dist-info/WHEEL
archicore-0.1.1.dist-info/top_level.txt
archicore-0.1.1.dist-info/RECORD
