Metadata-Version: 2.4
Name: archicore
Version: 0.1.1
Summary: Official Python SDK for ArchiCore Architecture Analysis API
Author-email: ArchiCore Team <support@archicore.io>
License: MIT
Project-URL: Homepage, https://archicore.io
Project-URL: Documentation, https://docs.archicore.io
Project-URL: Repository, https://github.com/archicore/archicore-python
Project-URL: Changelog, https://github.com/archicore/archicore-python/blob/main/CHANGELOG.md
Keywords: archicore,architecture,code-analysis,api,sdk,ai,llm
Classifier: Development Status :: 4 - Beta
Classifier: Intended Audience :: Developers
Classifier: License :: OSI Approved :: MIT License
Classifier: Operating System :: OS Independent
Classifier: Programming Language :: Python :: 3
Classifier: Programming Language :: Python :: 3.8
Classifier: Programming Language :: Python :: 3.9
Classifier: Programming Language :: Python :: 3.10
Classifier: Programming Language :: Python :: 3.11
Classifier: Programming Language :: Python :: 3.12
Classifier: Topic :: Software Development :: Libraries :: Python Modules
Classifier: Topic :: Software Development :: Quality Assurance
Requires-Python: >=3.8
License-File: LICENSE
Requires-Dist: requests>=2.28.0
Provides-Extra: dev
Requires-Dist: pytest>=7.0; extra == "dev"
Requires-Dist: pytest-cov>=4.0; extra == "dev"
Requires-Dist: black>=23.0; extra == "dev"
Requires-Dist: isort>=5.12; extra == "dev"
Requires-Dist: mypy>=1.0; extra == "dev"
Requires-Dist: types-requests>=2.28; extra == "dev"
Dynamic: license-file
